redisopy/__init__.py
redisopy/errors.py
redisopy/fields.py
redisopy/models.py
redisopy/base/__init__.py
redisopy/base/connection.py
redisopy/base/field.py
redisopy/base/mixin.py
redisopy/base/model.py
redisopy/containers/__init__.py
redisopy/containers/base.py
redisopy/containers/list.py
redisopy/containers/set.py
redisopy/utils/__init__.py
redisopy/utils/alias.py
redisopy/utils/model_var.py
redisopy/utils/validation.py
test/__init__.py
test/test_list.py
test/test_model.py
test/test_set.py
redisopy-0.0.7.dist-info/METADATA
redisopy-0.0.7.dist-info/WHEEL
redisopy-0.0.7.dist-info/top_level.txt
redisopy-0.0.7.dist-info/RECORD
