Metadata-Version: 2.1
Name: redisopy
Version: 0.0.7
Summary: python redis orm
Home-page: https://github.com/StevenLianaL/redisopy
Author: Steven Wang
Author-email: brightstar8284@icloud.com
Classifier: Programming Language :: Python :: 3.10
Classifier: License :: OSI Approved :: MIT License
Requires-Dist: redis (>=4.3.5)
Requires-Dist: pendulum (>=2.1.2)
